ha_unique123/__init__.py
ha_unique123-1.0.0.dist-info/METADATA
ha_unique123-1.0.0.dist-info/WHEEL
ha_unique123-1.0.0.dist-info/top_level.txt
ha_unique123-1.0.0.dist-info/RECORD
